mapbox_tilesets/__init__.py
mapbox_tilesets/errors.py
mapbox_tilesets/utils.py
mapbox_tilesets/scripts/__init__.py
mapbox_tilesets/scripts/cli.py
mapbox_tilesets-2.2.0.dist-info/licenses/LICENSE.md
mapbox_tilesets-2.2.0.dist-info/METADATA
mapbox_tilesets-2.2.0.dist-info/WHEEL
mapbox_tilesets-2.2.0.dist-info/entry_points.txt
mapbox_tilesets-2.2.0.dist-info/top_level.txt
mapbox_tilesets-2.2.0.dist-info/RECORD
