Metadata-Version: 2.4
Name: mapbox-tilesets
Version: 2.2.0
Summary: CLI for interacting with and preparing data for the Mapbox Tilesets API
Author-email: Mapbox <maps-api-team@mapbox.com>
License: BSD 2-Clause License
Keywords: mapbox,tilesets,cli,geojson,vector tiles
Classifier: Programming Language :: Python :: 3
Classifier: Programming Language :: Python :: 3 :: Only
Classifier: License :: OSI Approved :: BSD License
Classifier: Operating System :: OS Independent
Requires-Python: >=3.10
License-File: LICENSE.md
Requires-Dist: click>=8.1
Requires-Dist: cligj>=0.7
Requires-Dist: requests>=2.32
Requires-Dist: requests-toolbelt>=1.0
Requires-Dist: jsonschema<5,>=4.18
Requires-Dist: mercantile>=1.1
Requires-Dist: geojson>=3.0
Requires-Dist: numpy<2,>=1.23
Provides-Extra: estimate-area
Requires-Dist: supermercado>=0.2.0; extra == "estimate-area"
Provides-Extra: test
Requires-Dist: pre-commit>=3.5; extra == "test"
Requires-Dist: pytest>=8; extra == "test"
Requires-Dist: pytest-cov>=4; extra == "test"
Dynamic: license-file
